{"config":{"output_file":null,"full_docs":false,"pub_only":false,"reachable_only":false,"distro_crate":false,"signatures":false,"borrow_data":false},"version":"0.19.1","compilation":{"directory":"/Users/vilberg/sites/vilbergs/advent-of-code/2021/day-two","program":"/Users/vilberg/.rustup/toolchains/stable-x86_64-apple-darwin/bin/rls","arguments":[],"output":"/Users/vilberg/sites/vilbergs/advent-of-code/2021/day-two/target/rls/debug/deps/libday_two-3046c4d0a4fe7ef0.rmeta"},"prelude":{"crate_id":{"name":"day_two","disambiguator":[5764916835605009647,0]},"crate_root":"src","external_crates":[{"file_name":"/Users/vilberg/sites/vilbergs/advent-of-code/2021/day-two/src/main.rs","num":1,"id":{"name":"std","disambiguator":[7777094053559708767,0]}},{"file_name":"/Users/vilberg/sites/vilbergs/advent-of-code/2021/day-two/src/main.rs","num":2,"id":{"name":"core","disambiguator":[10550174156715778454,0]}},{"file_name":"/Users/vilberg/sites/vilbergs/advent-of-code/2021/day-two/src/main.rs","num":3,"id":{"name":"compiler_builtins","disambiguator":[8770346864682343241,0]}},{"file_name":"/Users/vilberg/sites/vilbergs/advent-of-code/2021/day-two/src/main.rs","num":4,"id":{"name":"rustc_std_workspace_core","disambiguator":[8196830942918118636,0]}},{"file_name":"/Users/vilberg/sites/vilbergs/advent-of-code/2021/day-two/src/main.rs","num":5,"id":{"name":"alloc","disambiguator":[12786826162718588903,0]}},{"file_name":"/Users/vilberg/sites/vilbergs/advent-of-code/2021/day-two/src/main.rs","num":6,"id":{"name":"libc","disambiguator":[7262382603413566750,0]}},{"file_name":"/Users/vilberg/sites/vilbergs/advent-of-code/2021/day-two/src/main.rs","num":7,"id":{"name":"unwind","disambiguator":[12233289566066112318,0]}},{"file_name":"/Users/vilberg/sites/vilbergs/advent-of-code/2021/day-two/src/main.rs","num":8,"id":{"name":"cfg_if","disambiguator":[4998072162051350919,0]}},{"file_name":"/Users/vilberg/sites/vilbergs/advent-of-code/2021/day-two/src/main.rs","num":9,"id":{"name":"hashbrown","disambiguator":[14817392966914922723,0]}},{"file_name":"/Users/vilberg/sites/vilbergs/advent-of-code/2021/day-two/src/main.rs","num":10,"id":{"name":"rustc_std_workspace_alloc","disambiguator":[13537029249427453884,0]}},{"file_name":"/Users/vilberg/sites/vilbergs/advent-of-code/2021/day-two/src/main.rs","num":11,"id":{"name":"rustc_demangle","disambiguator":[16172866892641339196,0]}},{"file_name":"/Users/vilberg/sites/vilbergs/advent-of-code/2021/day-two/src/main.rs","num":12,"id":{"name":"std_detect","disambiguator":[18226255698322429307,0]}},{"file_name":"/Users/vilberg/sites/vilbergs/advent-of-code/2021/day-two/src/main.rs","num":13,"id":{"name":"addr2line","disambiguator":[12872472635654720224,0]}},{"file_name":"/Users/vilberg/sites/vilbergs/advent-of-code/2021/day-two/src/main.rs","num":14,"id":{"name":"gimli","disambiguator":[15477836623066676988,0]}},{"file_name":"/Users/vilberg/sites/vilbergs/advent-of-code/2021/day-two/src/main.rs","num":15,"id":{"name":"object","disambiguator":[8883445751219211826,0]}},{"file_name":"/Users/vilberg/sites/vilbergs/advent-of-code/2021/day-two/src/main.rs","num":16,"id":{"name":"panic_unwind","disambiguator":[4189598673803333586,0]}}],"span":{"file_name":"src/main.rs","byte_start":0,"byte_end":1584,"line_start":1,"line_end":72,"column_start":1,"column_end":2}},"imports":[{"kind":"Use","ref_id":{"krate":1,"index":2951},"span":{"file_name":"src/main.rs","byte_start":9,"byte_end":11,"line_start":1,"line_end":1,"column_start":10,"column_end":12},"alias_span":null,"name":"fs","value":"","parent":{"krate":0,"index":0}}],"defs":[{"kind":"Mod","id":{"krate":0,"index":0},"span":{"file_name":"src/main.rs","byte_start":0,"byte_end":1584,"line_start":1,"line_end":72,"column_start":1,"column_end":2},"name":"","qualname":"::","value":"src/main.rs","parent":null,"children":[{"krate":0,"index":1},{"krate":0,"index":2},{"krate":0,"index":3},{"krate":0,"index":6},{"krate":0,"index":13},{"krate":0,"index":14},{"krate":0,"index":15},{"krate":0,"index":16}],"decl_id":null,"docs":"","sig":null,"attributes":[]},{"kind":"TupleVariant","id":{"krate":0,"index":7},"span":{"file_name":"src/main.rs","byte_start":35,"byte_end":42,"line_start":4,"line_end":4,"column_start":5,"column_end":12},"name":"Forward","qualname":"::Direction::Forward","value":"Direction::Forward","parent":{"krate":0,"index":6},"children":[],"decl_id":null,"docs":"","sig":null,"attributes":[]},{"kind":"TupleVariant","id":{"krate":0,"index":9},"span":{"file_name":"src/main.rs","byte_start":48,"byte_end":50,"line_start":5,"line_end":5,"column_start":5,"column_end":7},"name":"Up","qualname":"::Direction::Up","value":"Direction::Up","parent":{"krate":0,"index":6},"children":[],"decl_id":null,"docs":"","sig":null,"attributes":[]},{"kind":"TupleVariant","id":{"krate":0,"index":11},"span":{"file_name":"src/main.rs","byte_start":56,"byte_end":60,"line_start":6,"line_end":6,"column_start":5,"column_end":9},"name":"Down","qualname":"::Direction::Down","value":"Direction::Down","parent":{"krate":0,"index":6},"children":[],"decl_id":null,"docs":"","sig":null,"attributes":[]},{"kind":"Enum","id":{"krate":0,"index":6},"span":{"file_name":"src/main.rs","byte_start":19,"byte_end":28,"line_start":3,"line_end":3,"column_start":6,"column_end":15},"name":"Direction","qualname":"::Direction","value":"enum Direction { Forward, Up, Down, }","parent":null,"children":[{"krate":0,"index":7},{"krate":0,"index":9},{"krate":0,"index":11}],"decl_id":null,"docs":"","sig":null,"attributes":[]},{"kind":"Function","id":{"krate":0,"index":13},"span":{"file_name":"src/main.rs","byte_start":68,"byte_end":72,"line_start":9,"line_end":9,"column_start":4,"column_end":8},"name":"main","qualname":"::main","value":"fn main()","parent":null,"children":[],"decl_id":null,"docs":"","sig":null,"attributes":[]},{"kind":"Function","id":{"krate":0,"index":14},"span":{"file_name":"src/main.rs","byte_start":167,"byte_end":175,"line_start":14,"line_end":14,"column_start":4,"column_end":12},"name":"part_one","qualname":"::part_one","value":"fn part_one() -> i32","parent":null,"children":[],"decl_id":null,"docs":"","sig":null,"attributes":[]},{"kind":"Local","id":{"krate":0,"index":2684354574},"span":{"file_name":"src/main.rs","byte_start":195,"byte_end":200,"line_start":15,"line_end":15,"column_start":9,"column_end":14},"name":"input","qualname":"input$HirId { owner: DefId(0:14 ~ day_two[5001]::part_one), local_id: 5 }","value":"std::vec::Vec<(Direction, i32)>","parent":null,"children":[],"decl_id":null,"docs":"","sig":null,"attributes":[]},{"kind":"Local","id":{"krate":0,"index":2415919118},"span":{"file_name":"src/main.rs","byte_start":229,"byte_end":239,"line_start":16,"line_end":16,"column_start":13,"column_end":23},"name":"horizontal","qualname":"horizontal$HirId { owner: DefId(0:14 ~ day_two[5001]::part_one), local_id: 9 }","value":"i32","parent":null,"children":[],"decl_id":null,"docs":"","sig":null,"attributes":[]},{"kind":"Local","id":{"krate":0,"index":2952790030},"span":{"file_name":"src/main.rs","byte_start":257,"byte_end":262,"line_start":17,"line_end":17,"column_start":13,"column_end":18},"name":"depth","qualname":"depth$HirId { owner: DefId(0:14 ~ day_two[5001]::part_one), local_id: 13 }","value":"i32","parent":null,"children":[],"decl_id":null,"docs":"","sig":null,"attributes":[]},{"kind":"Local","id":{"krate":0,"index":3087007758},"span":{"file_name":"src/main.rs","byte_start":291,"byte_end":296,"line_start":19,"line_end":19,"column_start":23,"column_end":28},"name":"iter","qualname":"iter$HirId { owner: DefId(0:14 ~ day_two[5001]::part_one), local_id: 29 }","value":"std::vec::IntoIter<(Direction, i32)>","parent":null,"children":[],"decl_id":null,"docs":"","sig":null,"attributes":[]},{"kind":"Local","id":{"krate":0,"index":2281701390},"span":{"file_name":"src/main.rs","byte_start":291,"byte_end":296,"line_start":19,"line_end":19,"column_start":23,"column_end":28},"name":"__next","qualname":"__next$HirId { owner: DefId(0:14 ~ day_two[5001]::part_one), local_id: 17 }","value":"(Direction, i32)","parent":null,"children":[],"decl_id":null,"docs":"","sig":null,"attributes":[]},{"kind":"Local","id":{"krate":0,"index":1207959566},"span":{"file_name":"src/main.rs","byte_start":277,"byte_end":287,"line_start":19,"line_end":19,"column_start":9,"column_end":19},"name":"val","qualname":"val$HirId { owner: DefId(0:14 ~ day_two[5001]::part_one), local_id: 18 }","value":"(Direction, i32)","parent":null,"children":[],"decl_id":null,"docs":"","sig":null,"attributes":[]},{"kind":"Local","id":{"krate":0,"index":3825205262},"span":{"file_name":"src/main.rs","byte_start":278,"byte_end":281,"line_start":19,"line_end":19,"column_start":10,"column_end":13},"name":"pos","qualname":"pos$HirId { owner: DefId(0:14 ~ day_two[5001]::part_one), local_id: 39 }","value":"Direction","parent":null,"children":[],"decl_id":null,"docs":"","sig":null,"attributes":[]},{"kind":"Local","id":{"krate":0,"index":335544334},"span":{"file_name":"src/main.rs","byte_start":283,"byte_end":286,"line_start":19,"line_end":19,"column_start":15,"column_end":18},"name":"dir","qualname":"dir$HirId { owner: DefId(0:14 ~ day_two[5001]::part_one), local_id: 40 }","value":"i32","parent":null,"children":[],"decl_id":null,"docs":"","sig":null,"attributes":[]},{"kind":"Function","id":{"krate":0,"index":15},"span":{"file_name":"src/main.rs","byte_start":506,"byte_end":514,"line_start":30,"line_end":30,"column_start":4,"column_end":12},"name":"part_two","qualname":"::part_two","value":"fn part_two() -> i32","parent":null,"children":[],"decl_id":null,"docs":"","sig":null,"attributes":[]},{"kind":"Local","id":{"krate":0,"index":2684354575},"span":{"file_name":"src/main.rs","byte_start":534,"byte_end":539,"line_start":31,"line_end":31,"column_start":9,"column_end":14},"name":"input","qualname":"input$HirId { owner: DefId(0:15 ~ day_two[5001]::part_two), local_id: 5 }","value":"std::vec::Vec<(Direction, i32)>","parent":null,"children":[],"decl_id":null,"docs":"","sig":null,"attributes":[]},{"kind":"Local","id":{"krate":0,"index":2415919119},"span":{"file_name":"src/main.rs","byte_start":568,"byte_end":578,"line_start":32,"line_end":32,"column_start":13,"column_end":23},"name":"horizontal","qualname":"horizontal$HirId { owner: DefId(0:15 ~ day_two[5001]::part_two), local_id: 9 }","value":"i32","parent":null,"children":[],"decl_id":null,"docs":"","sig":null,"attributes":[]},{"kind":"Local","id":{"krate":0,"index":2952790031},"span":{"file_name":"src/main.rs","byte_start":596,"byte_end":601,"line_start":33,"line_end":33,"column_start":13,"column_end":18},"name":"depth","qualname":"depth$HirId { owner: DefId(0:15 ~ day_two[5001]::part_two), local_id: 13 }","value":"i32","parent":null,"children":[],"decl_id":null,"docs":"","sig":null,"attributes":[]},{"kind":"Local","id":{"krate":0,"index":2281701391},"span":{"file_name":"src/main.rs","byte_start":619,"byte_end":622,"line_start":34,"line_end":34,"column_start":13,"column_end":16},"name":"aim","qualname":"aim$HirId { owner: DefId(0:15 ~ day_two[5001]::part_two), local_id: 17 }","value":"i32","parent":null,"children":[],"decl_id":null,"docs":"","sig":null,"attributes":[]},{"kind":"Local","id":{"krate":0,"index":2214592527},"span":{"file_name":"src/main.rs","byte_start":651,"byte_end":656,"line_start":36,"line_end":36,"column_start":23,"column_end":28},"name":"iter","qualname":"iter$HirId { owner: DefId(0:15 ~ day_two[5001]::part_two), local_id: 33 }","value":"std::vec::IntoIter<(Direction, i32)>","parent":null,"children":[],"decl_id":null,"docs":"","sig":null,"attributes":[]},{"kind":"Local","id":{"krate":0,"index":2818572303},"span":{"file_name":"src/main.rs","byte_start":651,"byte_end":656,"line_start":36,"line_end":36,"column_start":23,"column_end":28},"name":"__next","qualname":"__next$HirId { owner: DefId(0:15 ~ day_two[5001]::part_two), local_id: 21 }","value":"(Direction, i32)","parent":null,"children":[],"decl_id":null,"docs":"","sig":null,"attributes":[]},{"kind":"Local","id":{"krate":0,"index":1744830479},"span":{"file_name":"src/main.rs","byte_start":637,"byte_end":647,"line_start":36,"line_end":36,"column_start":9,"column_end":19},"name":"val","qualname":"val$HirId { owner: DefId(0:15 ~ day_two[5001]::part_two), local_id: 22 }","value":"(Direction, i32)","parent":null,"children":[],"decl_id":null,"docs":"","sig":null,"attributes":[]},{"kind":"Local","id":{"krate":0,"index":3556769807},"span":{"file_name":"src/main.rs","byte_start":638,"byte_end":641,"line_start":36,"line_end":36,"column_start":10,"column_end":13},"name":"pos","qualname":"pos$HirId { owner: DefId(0:15 ~ day_two[5001]::part_two), local_id: 43 }","value":"Direction","parent":null,"children":[],"decl_id":null,"docs":"","sig":null,"attributes":[]},{"kind":"Local","id":{"krate":0,"index":872415247},"span":{"file_name":"src/main.rs","byte_start":643,"byte_end":646,"line_start":36,"line_end":36,"column_start":15,"column_end":18},"name":"dir","qualname":"dir$HirId { owner: DefId(0:15 ~ day_two[5001]::part_two), local_id: 44 }","value":"i32","parent":null,"children":[],"decl_id":null,"docs":"","sig":null,"attributes":[]},{"kind":"Function","id":{"krate":0,"index":16},"span":{"file_name":"src/main.rs","byte_start":930,"byte_end":940,"line_start":50,"line_end":50,"column_start":4,"column_end":14},"name":"load_input","qualname":"::load_input","value":"fn load_input() -> Vec<(Direction, i32)>","parent":null,"children":[],"decl_id":null,"docs":"","sig":null,"attributes":[]},{"kind":"Local","id":{"krate":0,"index":1342177296},"span":{"file_name":"src/main.rs","byte_start":978,"byte_end":986,"line_start":51,"line_end":51,"column_start":9,"column_end":17},"name":"contents","qualname":"contents$HirId { owner: DefId(0:16 ~ day_two[5001]::load_input), local_id: 10 }","value":"std::string::String","parent":null,"children":[],"decl_id":null,"docs":"","sig":null,"attributes":[]},{"kind":"Local","id":{"krate":0,"index":4194304016},"span":{"file_name":"src/main.rs","byte_start":1062,"byte_end":1067,"line_start":53,"line_end":53,"column_start":9,"column_end":14},"name":"parts","qualname":"parts$HirId { owner: DefId(0:16 ~ day_two[5001]::load_input), local_id: 95 }","value":"std::vec::Vec<(Direction, i32)>","parent":null,"children":[],"decl_id":null,"docs":"","sig":null,"attributes":[]},{"kind":"Local","id":{"krate":0,"index":2818572304},"span":{"file_name":"src/main.rs","byte_start":1126,"byte_end":1127,"line_start":56,"line_end":56,"column_start":15,"column_end":16},"name":"s","qualname":"$HirId { owner: DefId(0:16 ~ day_two[5001]::load_input), local_id: 91 }::s","value":"&str","parent":null,"children":[],"decl_id":null,"docs":"","sig":null,"attributes":[]},{"kind":"Local","id":{"krate":0,"index":939524112},"span":{"file_name":"src/main.rs","byte_start":1151,"byte_end":1162,"line_start":57,"line_end":57,"column_start":21,"column_end":32},"name":"pos_and_dir","qualname":"pos_and_dir$HirId { owner: DefId(0:16 ~ day_two[5001]::load_input), local_id: 28 }","value":"std::str::Split<&str>","parent":null,"children":[],"decl_id":null,"docs":"","sig":null,"attributes":[]},{"kind":"Local","id":{"krate":0,"index":2751463440},"span":{"file_name":"src/main.rs","byte_start":1195,"byte_end":1202,"line_start":58,"line_end":58,"column_start":17,"column_end":24},"name":"raw_pos","qualname":"raw_pos$HirId { owner: DefId(0:16 ~ day_two[5001]::load_input), local_id: 37 }","value":"&str","parent":null,"children":[],"decl_id":null,"docs":"","sig":null,"attributes":[]},{"kind":"Local","id":{"krate":0,"index":3791650832},"span":{"file_name":"src/main.rs","byte_start":1251,"byte_end":1254,"line_start":60,"line_end":60,"column_start":17,"column_end":20},"name":"pos","qualname":"pos$HirId { owner: DefId(0:16 ~ day_two[5001]::load_input), local_id: 71 }","value":"Direction","parent":null,"children":[],"decl_id":null,"docs":"","sig":null,"attributes":[]}],"impls":[],"refs":[{"kind":"Mod","span":{"file_name":"src/main.rs","byte_start":4,"byte_end":7,"line_start":1,"line_end":1,"column_start":5,"column_end":8},"ref_id":{"krate":1,"index":0}},{"kind":"Function","span":{"file_name":"src/main.rs","byte_start":106,"byte_end":114,"line_start":10,"line_end":10,"column_start":30,"column_end":38},"ref_id":{"krate":0,"index":14}},{"kind":"Function","span":{"file_name":"src/main.rs","byte_start":148,"byte_end":156,"line_start":11,"line_end":11,"column_start":30,"column_end":38},"ref_id":{"krate":0,"index":15}},{"kind":"Function","span":{"file_name":"src/main.rs","byte_start":203,"byte_end":213,"line_start":15,"line_end":15,"column_start":17,"column_end":27},"ref_id":{"krate":0,"index":16}},{"kind":"Variable","span":{"file_name":"src/main.rs","byte_start":291,"byte_end":296,"line_start":19,"line_end":19,"column_start":23,"column_end":28},"ref_id":{"krate":0,"index":2684354574}},{"kind":"Variable","span":{"file_name":"src/main.rs","byte_start":277,"byte_end":287,"line_start":19,"line_end":19,"column_start":9,"column_end":19},"ref_id":{"krate":2,"index":40265}},{"kind":"Variable","span":{"file_name":"src/main.rs","byte_start":313,"byte_end":316,"line_start":20,"line_end":20,"column_start":15,"column_end":18},"ref_id":{"krate":0,"index":3825205262}},{"kind":"Type","span":{"file_name":"src/main.rs","byte_start":342,"byte_end":349,"line_start":21,"line_end":21,"column_start":24,"column_end":31},"ref_id":{"krate":0,"index":7}},{"kind":"Type","span":{"file_name":"src/main.rs","byte_start":331,"byte_end":340,"line_start":21,"line_end":21,"column_start":13,"column_end":22},"ref_id":{"krate":0,"index":6}},{"kind":"Type","span":{"file_name":"src/main.rs","byte_start":342,"byte_end":349,"line_start":21,"line_end":21,"column_start":24,"column_end":31},"ref_id":{"krate":0,"index":7}},{"kind":"Type","span":{"file_name":"src/main.rs","byte_start":331,"byte_end":340,"line_start":21,"line_end":21,"column_start":13,"column_end":22},"ref_id":{"krate":0,"index":6}},{"kind":"Variable","span":{"file_name":"src/main.rs","byte_start":367,"byte_end":370,"line_start":21,"line_end":21,"column_start":49,"column_end":52},"ref_id":{"krate":0,"index":335544334}},{"kind":"Variable","span":{"file_name":"src/main.rs","byte_start":353,"byte_end":363,"line_start":21,"line_end":21,"column_start":35,"column_end":45},"ref_id":{"krate":0,"index":2415919118}},{"kind":"Type","span":{"file_name":"src/main.rs","byte_start":395,"byte_end":399,"line_start":22,"line_end":22,"column_start":24,"column_end":28},"ref_id":{"krate":0,"index":11}},{"kind":"Type","span":{"file_name":"src/main.rs","byte_start":384,"byte_end":393,"line_start":22,"line_end":22,"column_start":13,"column_end":22},"ref_id":{"krate":0,"index":6}},{"kind":"Type","span":{"file_name":"src/main.rs","byte_start":395,"byte_end":399,"line_start":22,"line_end":22,"column_start":24,"column_end":28},"ref_id":{"krate":0,"index":11}},{"kind":"Type","span":{"file_name":"src/main.rs","byte_start":384,"byte_end":393,"line_start":22,"line_end":22,"column_start":13,"column_end":22},"ref_id":{"krate":0,"index":6}},{"kind":"Variable","span":{"file_name":"src/main.rs","byte_start":412,"byte_end":415,"line_start":22,"line_end":22,"column_start":41,"column_end":44},"ref_id":{"krate":0,"index":335544334}},{"kind":"Variable","span":{"file_name":"src/main.rs","byte_start":403,"byte_end":408,"line_start":22,"line_end":22,"column_start":32,"column_end":37},"ref_id":{"krate":0,"index":2952790030}},{"kind":"Type","span":{"file_name":"src/main.rs","byte_start":440,"byte_end":442,"line_start":23,"line_end":23,"column_start":24,"column_end":26},"ref_id":{"krate":0,"index":9}},{"kind":"Type","span":{"file_name":"src/main.rs","byte_start":429,"byte_end":438,"line_start":23,"line_end":23,"column_start":13,"column_end":22},"ref_id":{"krate":0,"index":6}},{"kind":"Type","span":{"file_name":"src/main.rs","byte_start":440,"byte_end":442,"line_start":23,"line_end":23,"column_start":24,"column_end":26},"ref_id":{"krate":0,"index":9}},{"kind":"Type","span":{"file_name":"src/main.rs","byte_start":429,"byte_end":438,"line_start":23,"line_end":23,"column_start":13,"column_end":22},"ref_id":{"krate":0,"index":6}},{"kind":"Variable","span":{"file_name":"src/main.rs","byte_start":455,"byte_end":458,"line_start":23,"line_end":23,"column_start":39,"column_end":42},"ref_id":{"krate":0,"index":335544334}},{"kind":"Variable","span":{"file_name":"src/main.rs","byte_start":446,"byte_end":451,"line_start":23,"line_end":23,"column_start":30,"column_end":35},"ref_id":{"krate":0,"index":2952790030}},{"kind":"Variable","span":{"file_name":"src/main.rs","byte_start":481,"byte_end":491,"line_start":27,"line_end":27,"column_start":5,"column_end":15},"ref_id":{"krate":0,"index":2415919118}},{"kind":"Variable","span":{"file_name":"src/main.rs","byte_start":494,"byte_end":499,"line_start":27,"line_end":27,"column_start":18,"column_end":23},"ref_id":{"krate":0,"index":2952790030}},{"kind":"Function","span":{"file_name":"src/main.rs","byte_start":542,"byte_end":552,"line_start":31,"line_end":31,"column_start":17,"column_end":27},"ref_id":{"krate":0,"index":16}},{"kind":"Variable","span":{"file_name":"src/main.rs","byte_start":651,"byte_end":656,"line_start":36,"line_end":36,"column_start":23,"column_end":28},"ref_id":{"krate":0,"index":2684354575}},{"kind":"Variable","span":{"file_name":"src/main.rs","byte_start":637,"byte_end":647,"line_start":36,"line_end":36,"column_start":9,"column_end":19},"ref_id":{"krate":2,"index":40265}},{"kind":"Variable","span":{"file_name":"src/main.rs","byte_start":673,"byte_end":676,"line_start":37,"line_end":37,"column_start":15,"column_end":18},"ref_id":{"krate":0,"index":3556769807}},{"kind":"Type","span":{"file_name":"src/main.rs","byte_start":702,"byte_end":706,"line_start":38,"line_end":38,"column_start":24,"column_end":28},"ref_id":{"krate":0,"index":11}},{"kind":"Type","span":{"file_name":"src/main.rs","byte_start":691,"byte_end":700,"line_start":38,"line_end":38,"column_start":13,"column_end":22},"ref_id":{"krate":0,"index":6}},{"kind":"Type","span":{"file_name":"src/main.rs","byte_start":702,"byte_end":706,"line_start":38,"line_end":38,"column_start":24,"column_end":28},"ref_id":{"krate":0,"index":11}},{"kind":"Type","span":{"file_name":"src/main.rs","byte_start":691,"byte_end":700,"line_start":38,"line_end":38,"column_start":13,"column_end":22},"ref_id":{"krate":0,"index":6}},{"kind":"Variable","span":{"file_name":"src/main.rs","byte_start":717,"byte_end":720,"line_start":38,"line_end":38,"column_start":39,"column_end":42},"ref_id":{"krate":0,"index":872415247}},{"kind":"Variable","span":{"file_name":"src/main.rs","byte_start":710,"byte_end":713,"line_start":38,"line_end":38,"column_start":32,"column_end":35},"ref_id":{"krate":0,"index":2281701391}},{"kind":"Type","span":{"file_name":"src/main.rs","byte_start":745,"byte_end":747,"line_start":39,"line_end":39,"column_start":24,"column_end":26},"ref_id":{"krate":0,"index":9}},{"kind":"Type","span":{"file_name":"src/main.rs","byte_start":734,"byte_end":743,"line_start":39,"line_end":39,"column_start":13,"column_end":22},"ref_id":{"krate":0,"index":6}},{"kind":"Type","span":{"file_name":"src/main.rs","byte_start":745,"byte_end":747,"line_start":39,"line_end":39,"column_start":24,"column_end":26},"ref_id":{"krate":0,"index":9}},{"kind":"Type","span":{"file_name":"src/main.rs","byte_start":734,"byte_end":743,"line_start":39,"line_end":39,"column_start":13,"column_end":22},"ref_id":{"krate":0,"index":6}},{"kind":"Variable","span":{"file_name":"src/main.rs","byte_start":758,"byte_end":761,"line_start":39,"line_end":39,"column_start":37,"column_end":40},"ref_id":{"krate":0,"index":872415247}},{"kind":"Variable","span":{"file_name":"src/main.rs","byte_start":751,"byte_end":754,"line_start":39,"line_end":39,"column_start":30,"column_end":33},"ref_id":{"krate":0,"index":2281701391}},{"kind":"Type","span":{"file_name":"src/main.rs","byte_start":786,"byte_end":793,"line_start":40,"line_end":40,"column_start":24,"column_end":31},"ref_id":{"krate":0,"index":7}},{"kind":"Type","span":{"file_name":"src/main.rs","byte_start":775,"byte_end":784,"line_start":40,"line_end":40,"column_start":13,"column_end":22},"ref_id":{"krate":0,"index":6}},{"kind":"Type","span":{"file_name":"src/main.rs","byte_start":786,"byte_end":793,"line_start":40,"line_end":40,"column_start":24,"column_end":31},"ref_id":{"krate":0,"index":7}},{"kind":"Type","span":{"file_name":"src/main.rs","byte_start":775,"byte_end":784,"line_start":40,"line_end":40,"column_start":13,"column_end":22},"ref_id":{"krate":0,"index":6}},{"kind":"Variable","span":{"file_name":"src/main.rs","byte_start":829,"byte_end":832,"line_start":41,"line_end":41,"column_start":31,"column_end":34},"ref_id":{"krate":0,"index":872415247}},{"kind":"Variable","span":{"file_name":"src/main.rs","byte_start":815,"byte_end":825,"line_start":41,"line_end":41,"column_start":17,"column_end":27},"ref_id":{"krate":0,"index":2415919119}},{"kind":"Variable","span":{"file_name":"src/main.rs","byte_start":859,"byte_end":862,"line_start":42,"line_end":42,"column_start":26,"column_end":29},"ref_id":{"krate":0,"index":2281701391}},{"kind":"Variable","span":{"file_name":"src/main.rs","byte_start":865,"byte_end":868,"line_start":42,"line_end":42,"column_start":32,"column_end":35},"ref_id":{"krate":0,"index":872415247}},{"kind":"Variable","span":{"file_name":"src/main.rs","byte_start":850,"byte_end":855,"line_start":42,"line_end":42,"column_start":17,"column_end":22},"ref_id":{"krate":0,"index":2952790031}},{"kind":"Variable","span":{"file_name":"src/main.rs","byte_start":905,"byte_end":915,"line_start":47,"line_end":47,"column_start":5,"column_end":15},"ref_id":{"krate":0,"index":2415919119}},{"kind":"Variable","span":{"file_name":"src/main.rs","byte_start":918,"byte_end":923,"line_start":47,"line_end":47,"column_start":18,"column_end":23},"ref_id":{"krate":0,"index":2952790031}},{"kind":"Type","span":{"file_name":"src/main.rs","byte_start":946,"byte_end":949,"line_start":50,"line_end":50,"column_start":20,"column_end":23},"ref_id":{"krate":5,"index":6801}},{"kind":"Type","span":{"file_name":"src/main.rs","byte_start":951,"byte_end":960,"line_start":50,"line_end":50,"column_start":25,"column_end":34},"ref_id":{"krate":0,"index":6}},{"kind":"Function","span":{"file_name":"src/main.rs","byte_start":1021,"byte_end":1027,"line_start":51,"line_end":51,"column_start":52,"column_end":58},"ref_id":{"krate":2,"index":8319}},{"kind":"Function","span":{"file_name":"src/main.rs","byte_start":993,"byte_end":1007,"line_start":51,"line_end":51,"column_start":24,"column_end":38},"ref_id":{"krate":1,"index":3019}},{"kind":"Mod","span":{"file_name":"src/main.rs","byte_start":989,"byte_end":991,"line_start":51,"line_end":51,"column_start":20,"column_end":22},"ref_id":{"krate":1,"index":2951}},{"kind":"Function","span":{"file_name":"src/main.rs","byte_start":1561,"byte_end":1568,"line_start":69,"line_end":69,"column_start":10,"column_end":17},"ref_id":{"krate":2,"index":7440}},{"kind":"Function","span":{"file_name":"src/main.rs","byte_start":1121,"byte_end":1124,"line_start":56,"line_end":56,"column_start":10,"column_end":13},"ref_id":{"krate":2,"index":7402}},{"kind":"Function","span":{"file_name":"src/main.rs","byte_start":1104,"byte_end":1109,"line_start":55,"line_end":55,"column_start":10,"column_end":15},"ref_id":{"krate":2,"index":11867}},{"kind":"Function","span":{"file_name":"src/main.rs","byte_start":1088,"byte_end":1092,"line_start":54,"line_end":54,"column_start":10,"column_end":14},"ref_id":{"krate":2,"index":11926}},{"kind":"Variable","span":{"file_name":"src/main.rs","byte_start":1070,"byte_end":1078,"line_start":53,"line_end":53,"column_start":17,"column_end":25},"ref_id":{"krate":0,"index":1342177296}},{"kind":"Function","span":{"file_name":"src/main.rs","byte_start":1167,"byte_end":1172,"line_start":57,"line_end":57,"column_start":37,"column_end":42},"ref_id":{"krate":2,"index":11887}},{"kind":"Variable","span":{"file_name":"src/main.rs","byte_start":1165,"byte_end":1166,"line_start":57,"line_end":57,"column_start":35,"column_end":36},"ref_id":{"krate":0,"index":2818572304}},{"kind":"Function","span":{"file_name":"src/main.rs","byte_start":1224,"byte_end":1230,"line_start":58,"line_end":58,"column_start":46,"column_end":52},"ref_id":{"krate":2,"index":7833}},{"kind":"Function","span":{"file_name":"src/main.rs","byte_start":1217,"byte_end":1221,"line_start":58,"line_end":58,"column_start":39,"column_end":43},"ref_id":{"krate":2,"index":7385}},{"kind":"Variable","span":{"file_name":"src/main.rs","byte_start":1205,"byte_end":1216,"line_start":58,"line_end":58,"column_start":27,"column_end":38},"ref_id":{"krate":0,"index":939524112}},{"kind":"Variable","span":{"file_name":"src/main.rs","byte_start":1263,"byte_end":1270,"line_start":60,"line_end":60,"column_start":29,"column_end":36},"ref_id":{"krate":0,"index":2751463440}},{"kind":"Type","span":{"file_name":"src/main.rs","byte_start":1313,"byte_end":1320,"line_start":61,"line_end":61,"column_start":41,"column_end":48},"ref_id":{"krate":0,"index":7}},{"kind":"Type","span":{"file_name":"src/main.rs","byte_start":1302,"byte_end":1311,"line_start":61,"line_end":61,"column_start":30,"column_end":39},"ref_id":{"krate":0,"index":6}},{"kind":"Type","span":{"file_name":"src/main.rs","byte_start":1357,"byte_end":1359,"line_start":62,"line_end":62,"column_start":36,"column_end":38},"ref_id":{"krate":0,"index":9}},{"kind":"Type","span":{"file_name":"src/main.rs","byte_start":1346,"byte_end":1355,"line_start":62,"line_end":62,"column_start":25,"column_end":34},"ref_id":{"krate":0,"index":6}},{"kind":"Type","span":{"file_name":"src/main.rs","byte_start":1398,"byte_end":1402,"line_start":63,"line_end":63,"column_start":38,"column_end":42},"ref_id":{"krate":0,"index":11}},{"kind":"Type","span":{"file_name":"src/main.rs","byte_start":1387,"byte_end":1396,"line_start":63,"line_end":63,"column_start":27,"column_end":36},"ref_id":{"krate":0,"index":6}},{"kind":"Variable","span":{"file_name":"src/main.rs","byte_start":1483,"byte_end":1486,"line_start":67,"line_end":67,"column_start":14,"column_end":17},"ref_id":{"krate":0,"index":3791650832}},{"kind":"Function","span":{"file_name":"src/main.rs","byte_start":1531,"byte_end":1537,"line_start":67,"line_end":67,"column_start":62,"column_end":68},"ref_id":{"krate":2,"index":8320}},{"kind":"Function","span":{"file_name":"src/main.rs","byte_start":1516,"byte_end":1521,"line_start":67,"line_end":67,"column_start":47,"column_end":52},"ref_id":{"krate":2,"index":11955}},{"kind":"Function","span":{"file_name":"src/main.rs","byte_start":1507,"byte_end":1513,"line_start":67,"line_end":67,"column_start":38,"column_end":44},"ref_id":{"krate":2,"index":7833}},{"kind":"Function","span":{"file_name":"src/main.rs","byte_start":1500,"byte_end":1504,"line_start":67,"line_end":67,"column_start":31,"column_end":35},"ref_id":{"krate":2,"index":7385}},{"kind":"Variable","span":{"file_name":"src/main.rs","byte_start":1488,"byte_end":1499,"line_start":67,"line_end":67,"column_start":19,"column_end":30},"ref_id":{"krate":0,"index":939524112}},{"kind":"Variable","span":{"file_name":"src/main.rs","byte_start":1577,"byte_end":1582,"line_start":71,"line_end":71,"column_start":5,"column_end":10},"ref_id":{"krate":0,"index":4194304016}}],"macro_refs":[],"relations":[]}